BiblioDig_Py/__init__.py
BiblioDig_Py/books.csv
BiblioDig_Py/buscador_libros.py
BiblioDig-1.0.1.dist-info/METADATA
BiblioDig-1.0.1.dist-info/WHEEL
BiblioDig-1.0.1.dist-info/top_level.txt
BiblioDig-1.0.1.dist-info/RECORD
